airflow_deploy_softwrd/__init__.py
airflow_deploy_softwrd/app.py
airflow_deploy_softwrd-0.0.9.dist-info/licenses/LICENSE
airflow_deploy_softwrd-0.0.9.dist-info/METADATA
airflow_deploy_softwrd-0.0.9.dist-info/WHEEL
airflow_deploy_softwrd-0.0.9.dist-info/entry_points.txt
airflow_deploy_softwrd-0.0.9.dist-info/top_level.txt
airflow_deploy_softwrd-0.0.9.dist-info/RECORD
