Metadata-Version: 2.4
Name: airflow_deploy_softwrd
Version: 0.0.9
Summary: A Flask application to handle postman webhooks for deploying and taking down repositories.
Home-page: https://github.com/softwrdai/airflow_deploy_softwrd
Author: Md Robiuddin
Author-email: robiuddin@softwrd.ai
Classifier: Programming Language :: Python :: 3
Classifier: License :: OSI Approved :: Apache Software License
Classifier: Operating System :: Microsoft :: Windows
Requires-Python: >=3.9
License-File: LICENSE
Requires-Dist: Flask
Requires-Dist: boto3
Dynamic: author
Dynamic: author-email
Dynamic: classifier
Dynamic: description
Dynamic: description-content-type
Dynamic: home-page
Dynamic: license-file
Dynamic: requires-dist
Dynamic: requires-python
Dynamic: summary
